topsis/__init__.py
topsis/__main__.py
Topsis_SimranMalik_102003680-0.0.0.dist-info/LICENSE
Topsis_SimranMalik_102003680-0.0.0.dist-info/METADATA
Topsis_SimranMalik_102003680-0.0.0.dist-info/WHEEL
Topsis_SimranMalik_102003680-0.0.0.dist-info/entry_points.txt
Topsis_SimranMalik_102003680-0.0.0.dist-info/top_level.txt
Topsis_SimranMalik_102003680-0.0.0.dist-info/RECORD
