Metadata-Version: 2.1
Name: Topsis-SimranMalik-102003680
Version: 0.0.0
Summary: Topsis Implementation
Home-page: https://github.com/Simran509/Topsis-SimranMalik-102003680
Author: Simran Malik
Author-email: smalik_be20@thapar.edu
License: MIT
Classifier: License :: OSI Approved :: MIT License
Classifier: Programming Language :: Python :: 3.6
Classifier: Programming Language :: Python :: 3.7
Classifier: Programming Language :: Python :: 3.8
License-File: LICENSE
